mlmc/__init__.py
mlmc/estimator.py
mlmc/level_simulation.py
mlmc/moments.py
mlmc/sample_storage.py
mlmc/sample_storage_hdf.py
mlmc/sampler.py
mlmc/sampling_pool.py
mlmc/sampling_pool_pbs.py
mlmc/plot/__init__.py
mlmc/plot/diagnostic_plots.py
mlmc/plot/plots.py
mlmc/plot/violinplot.py
mlmc/quantity/__init__.py
mlmc/quantity/quantity.py
mlmc/quantity/quantity_estimate.py
mlmc/quantity/quantity_spec.py
mlmc/quantity/quantity_types.py
mlmc/random/__init__.py
mlmc/random/correlated_field.py
mlmc/sim/__init__.py
mlmc/sim/simulation.py
mlmc/sim/synth_simulation.py
mlmc/tool/__init__.py
mlmc/tool/distribution.py
mlmc/tool/flow_mc.py
mlmc/tool/gmsh_io.py
mlmc/tool/hdf5.py
mlmc/tool/pbs_job.py
mlmc/tool/process_base.py
mlmc/tool/simple_distribution.py
mlmc/tool/stats_tests.py
mlmc-1.0.3.dist-info/METADATA
mlmc-1.0.3.dist-info/WHEEL
mlmc-1.0.3.dist-info/top_level.txt
mlmc-1.0.3.dist-info/RECORD
