Metadata-Version: 2.1
Name: mlmc
Version: 1.0.3
Summary: Multilevel Monte Carlo method.
Home-page: https://github.com/GeoMop/MLMC
Author: Jan Brezina, Martin Spetlik
Author-email: jan.brezina@tul.cz
License: GPL 3.0
Classifier: Development Status :: 3 - Alpha
Classifier: Intended Audience :: Science/Research
Classifier: License :: OSI Approved :: GNU General Public License v3 or later (GPLv3+)
Classifier: Operating System :: Unix
Classifier: Operating System :: POSIX
Classifier: Operating System :: Microsoft :: Windows
Classifier: Programming Language :: Python :: 3
Classifier: Programming Language :: Python :: Implementation :: CPython
Classifier: Programming Language :: Python :: Implementation :: PyPy
Classifier: Topic :: Scientific/Engineering
Requires-Dist: numpy
Requires-Dist: scipy
Requires-Dist: scikit-learn
Requires-Dist: h5py >=3.1.0
Requires-Dist: ruamel.yaml
Requires-Dist: attrs
Requires-Dist: gstools
Requires-Dist: memoization
